{"name":"C5 Syntactic Analyser","tagline":"A php & javascript CoNLL format data dependency parsing and syntactic analysis tool","body":"# C5 Syntactic Analyser\r\n============\r\n\r\nA php & javascript CoNLL format data dependency parsing and syntactic analysis tool\r\n\r\nThis is a dependancy parser that uses the arc-eager shift-reduce algorithm for parsing text strings \r\nand the C5.0 decision tree machine learning algorithm to predict correcr moves for parsing.","google":"","note":"Don't delete this file! It's used internally to help with page regeneration."}